FPGA-Traffic-Light-Controller-main/rtl/traffic_light_controller.v
// =============================================================================
// Module      : traffic_light_controller
// Project     : FPGA-Based Traffic Light Controller
// Author      : VLSI Student Project
// Description : 4-state FSM-based traffic light controller for North-South
//               and East-West directions with clock divider and timer logic.
//
// States:
//   S0 : NS Green,  EW Red    (NS traffic flows)
//   S1 : NS Yellow, EW Red    (NS warning)
//   S2 : NS Red,    EW Green  (EW traffic flows)
//   S3 : NS Red,    EW Yellow (EW warning)
//
// Outputs (active HIGH):
//   ns_red, ns_yellow, ns_green  — North-South lights
//   ew_red, ew_yellow, ew_green  — East-West lights
// =============================================================================

`timescale 1ns / 1ps

module traffic_light_controller (
    input  wire clk,        // System clock
    input  wire rst_n,      // Active-low synchronous reset
    output reg  ns_red,     // North-South Red
    output reg  ns_yellow,  // North-South Yellow
    output reg  ns_green,   // North-South Green
    output reg  ew_red,     // East-West Red
    output reg  ew_yellow,  // East-West Yellow
    output reg  ew_green    // East-West Green
);

    // =========================================================================
    // PARAMETERS — Adjust these for simulation vs real FPGA timing
    // =========================================================================
    // For simulation: small counts (easy to verify in waveform)
    // For FPGA 50 MHz clock: GREEN=2500000 (~50ms), YELLOW=1000000 (~20ms)
    // For real-world: GREEN=2500000000 (~50s), YELLOW=1000000000 (~20s)
    parameter GREEN_TIME  = 4'd10;   // 10 clock ticks (sim) / change for FPGA
    parameter YELLOW_TIME = 4'd3;    // 3 clock ticks  (sim)

    // =========================================================================
    // STATE ENCODING — One-hot or binary
    // =========================================================================
    localparam [1:0]
        S0 = 2'b00,  // NS Green,  EW Red
        S1 = 2'b01,  // NS Yellow, EW Red
        S2 = 2'b10,  // NS Red,    EW Green
        S3 = 2'b11;  // NS Red,    EW Yellow

    // =========================================================================
    // INTERNAL SIGNALS
    // =========================================================================
    reg [1:0]  state, next_state;          // Current and next FSM state
    reg [27:0] timer;                      // Timer counter for state duration
    wire       timer_done;                 // Timer expiry signal

    // =========================================================================
    // CLOCK DIVIDER (optional — used when driving from fast FPGA clock)
    // For simulation we use the raw clock directly; for FPGA instantiate
    // clock_divider module and feed its output here instead.
    // =========================================================================

    // =========================================================================
    // TIMER LOGIC — counts clock ticks per state
    // =========================================================================
    always @(posedge clk) begin
        if (!rst_n) begin
            timer <= 28'd0;
        end else if (timer_done) begin
            timer <= 28'd0;         // Reset when limit reached
        end else begin
            timer <= timer + 1'b1;
        end
    end

    // Timer done: depends on current state's duration
    assign timer_done = ((state == S0 || state == S2) && (timer == GREEN_TIME  - 1)) ||
                        ((state == S1 || state == S3) && (timer == YELLOW_TIME - 1));

    // =========================================================================
    // FSM — State Register (Sequential)
    // =========================================================================
    always @(posedge clk) begin
        if (!rst_n)
            state <= S0;
        else if (timer_done)
            state <= next_state;
    end

    // =========================================================================
    // FSM — Next-State Logic (Combinational)
    // =========================================================================
    always @(*) begin
        case (state)
            S0: next_state = S1;  // NS Green  → NS Yellow
            S1: next_state = S2;  // NS Yellow → EW Green
            S2: next_state = S3;  // EW Green  → EW Yellow
            S3: next_state = S0;  // EW Yellow → NS Green (cycle repeat)
            default: next_state = S0;
        endcase
    end

    // =========================================================================
    // OUTPUT LOGIC (Combinational — Moore FSM outputs depend only on state)
    // =========================================================================
    always @(*) begin
        // Default all outputs LOW (safe state)
        {ns_red, ns_yellow, ns_green} = 3'b100; // Default: NS Red
        {ew_red, ew_yellow, ew_green} = 3'b100; // Default: EW Red

        case (state)
            S0: begin // NS Green, EW Red
                ns_red = 1'b0; ns_yellow = 1'b0; ns_green = 1'b1;
                ew_red = 1'b1; ew_yellow = 1'b0; ew_green = 1'b0;
            end
            S1: begin // NS Yellow, EW Red
                ns_red = 1'b0; ns_yellow = 1'b1; ns_green = 1'b0;
                ew_red = 1'b1; ew_yellow = 1'b0; ew_green = 1'b0;
            end
            S2: begin // NS Red, EW Green
                ns_red = 1'b1; ns_yellow = 1'b0; ns_green = 1'b0;
                ew_red = 1'b0; ew_yellow = 1'b0; ew_green = 1'b1;
            end
            S3: begin // NS Red, EW Yellow
                ns_red = 1'b1; ns_yellow = 1'b0; ns_green = 1'b0;
                ew_red = 1'b0; ew_yellow = 1'b1; ew_green = 1'b0;
            end
            default: begin
                ns_red = 1'b1; ns_yellow = 1'b0; ns_green = 1'b0;
                ew_red = 1'b1; ew_yellow = 1'b0; ew_green = 1'b0;
            end
        endcase
    end

endmodule

FPGA-Traffic-Light-Controller-main/tb/tb_traffic_light_controller.v
// =============================================================================
// Module      : tb_traffic_light_controller
// Project     : FPGA-Based Traffic Light Controller
// Description : Self-checking testbench. Tests:
//               1. Reset behavior
//               2. Full FSM cycle (S0 → S1 → S2 → S3 → S0)
//               3. Output correctness per state
//               4. Timer accuracy
//
// Simulation Tools : ModelSim, Vivado Simulator, EDA Playground, Icarus Verilog
// Run command (Icarus): iverilog -o sim tb_traffic_light_controller.v
//                        traffic_light_controller.v && vvp sim
// =============================================================================

`timescale 1ns / 1ps

module tb_traffic_light_controller;

    // =========================================================================
    // PARAMETERS (must match DUT parameters)
    // =========================================================================
    parameter GREEN_TIME  = 4'd10;
    parameter YELLOW_TIME = 4'd3;

    // =========================================================================
    // SIGNALS
    // =========================================================================
    reg  clk;
    reg  rst_n;
    wire ns_red, ns_yellow, ns_green;
    wire ew_red, ew_yellow, ew_green;

    // =========================================================================
    // DUT INSTANTIATION
    // =========================================================================
    traffic_light_controller #(
        .GREEN_TIME (GREEN_TIME),
        .YELLOW_TIME(YELLOW_TIME)
    ) dut (
        .clk       (clk),
        .rst_n     (rst_n),
        .ns_red    (ns_red),
        .ns_yellow (ns_yellow),
        .ns_green  (ns_green),
        .ew_red    (ew_red),
        .ew_yellow (ew_yellow),
        .ew_green  (ew_green)
    );

    // =========================================================================
    // CLOCK GENERATION — 10 ns period = 100 MHz
    // =========================================================================
    initial clk = 0;
    always #5 clk = ~clk;  // Toggle every 5 ns → 10 ns period

    // =========================================================================
    // TASK: Print current state of all outputs
    // =========================================================================
    task print_outputs;
        input [63:0] timestamp;
        begin
            $display("T=%0t | NS[R=%b Y=%b G=%b] | EW[R=%b Y=%b G=%b]",
                     timestamp,
                     ns_red, ns_yellow, ns_green,
                     ew_red, ew_yellow, ew_green);
        end
    endtask

    // =========================================================================
    // TASK: Check expected output and flag errors
    // =========================================================================
    integer error_count;

    task check_state;
        input [2:0] exp_ns;  // {ns_red, ns_yellow, ns_green}
        input [2:0] exp_ew;  // {ew_red, ew_yellow, ew_green}
        input [31:0] state_id;
        begin
            if ({ns_red, ns_yellow, ns_green} !== exp_ns ||
                {ew_red, ew_yellow, ew_green} !== exp_ew) begin
                $display("FAIL [S%0d] T=%0t | Got NS=%b EW=%b | Expected NS=%b EW=%b",
                         state_id, $time,
                         {ns_red, ns_yellow, ns_green},
                         {ew_red, ew_yellow, ew_green},
                         exp_ns, exp_ew);
                error_count = error_count + 1;
            end else begin
                $display("PASS [S%0d] T=%0t | NS=%b EW=%b ✓",
                         state_id, $time,
                         {ns_red, ns_yellow, ns_green},
                         {ew_red, ew_yellow, ew_green});
            end
        end
    endtask

    // =========================================================================
    // VCD DUMP — For waveform viewing in GTKWave or Vivado
    // =========================================================================
    initial begin
        $dumpfile("waveforms/traffic_light_sim.vcd");
        $dumpvars(0, tb_traffic_light_controller);
    end

    // =========================================================================
    // MAIN STIMULUS
    // =========================================================================
    initial begin
        error_count = 0;

        // -----------------------------------------------
        // Banner
        // -----------------------------------------------
        $display("============================================================");
        $display(" FPGA Traffic Light Controller — Testbench Simulation");
        $display("============================================================");
        $display(" GREEN_TIME  = %0d ticks", GREEN_TIME);
        $display(" YELLOW_TIME = %0d ticks", YELLOW_TIME);
        $display("------------------------------------------------------------");

        // -----------------------------------------------
        // TEST 1: Reset Behavior
        // -----------------------------------------------
        $display("\n--- TEST 1: Reset Assertion ---");
        rst_n = 0;         // Assert reset
        repeat(5) @(posedge clk);
        #1;
        $display("T=%0t | rst_n=0 | NS[R=%b Y=%b G=%b] | EW[R=%b Y=%b G=%b]",
                 $time, ns_red, ns_yellow, ns_green, ew_red, ew_yellow, ew_green);
        // After reset, expect S0: NS Green, EW Red → NS=001, EW=100
        check_state(3'b001, 3'b100, 0);

        // -----------------------------------------------
        // TEST 2: Release reset, observe S0 (NS Green)
        // -----------------------------------------------
        $display("\n--- TEST 2: S0 — NS Green, EW Red ---");
        rst_n = 1;
        repeat(2) @(posedge clk); #1;
        check_state(3'b001, 3'b100, 0);
        $display("  NS Green ON, EW Red ON — vehicles flow NS");

        // -----------------------------------------------
        // TEST 3: Wait through GREEN state → enter S1 (NS Yellow)
        // -----------------------------------------------
        $display("\n--- TEST 3: S1 — NS Yellow, EW Red ---");
        repeat(GREEN_TIME) @(posedge clk); #1;
        check_state(3'b010, 3'b100, 1);
        $display("  NS Yellow ON — warning, NS traffic should stop");

        // -----------------------------------------------
        // TEST 4: Wait through YELLOW → enter S2 (EW Green)
        // -----------------------------------------------
        $display("\n--- TEST 4: S2 — NS Red, EW Green ---");
        repeat(YELLOW_TIME) @(posedge clk); #1;
        check_state(3'b100, 3'b001, 2);
        $display("  EW Green ON — vehicles flow EW");

        // -----------------------------------------------
        // TEST 5: Wait through GREEN → enter S3 (EW Yellow)
        // -----------------------------------------------
        $display("\n--- TEST 5: S3 — NS Red, EW Yellow ---");
        repeat(GREEN_TIME) @(posedge clk); #1;
        check_state(3'b100, 3'b010, 3);
        $display("  EW Yellow ON — warning, EW traffic should stop");

        // -----------------------------------------------
        // TEST 6: Full cycle returns to S0 (NS Green)
        // -----------------------------------------------
        $display("\n--- TEST 6: Back to S0 — Cycle Complete ---");
        repeat(YELLOW_TIME) @(posedge clk); #1;
        check_state(3'b001, 3'b100, 0);
        $display("  Full cycle completed. FSM returned to S0 ✓");

        // -----------------------------------------------
        // TEST 7: Reset in mid-cycle
        // -----------------------------------------------
        $display("\n--- TEST 7: Mid-cycle Reset ---");
        repeat(5) @(posedge clk);    // advance a few ticks into S0
        rst_n = 0;
        @(posedge clk); #1;
        check_state(3'b001, 3'b100, 0);  // Must snap back to S0
        rst_n = 1;
        $display("  Mid-cycle reset OK — returned to S0 ✓");

        // -----------------------------------------------
        // TEST 8: Run one more full cycle to confirm stability
        // -----------------------------------------------
        $display("\n--- TEST 8: Second Full Cycle Verification ---");
        repeat(GREEN_TIME + YELLOW_TIME + GREEN_TIME + YELLOW_TIME + 2) @(posedge clk);
        #1;
        check_state(3'b001, 3'b100, 0);
        $display("  Second cycle stable ✓");

        // -----------------------------------------------
        // SUMMARY
        // -----------------------------------------------
        $display("\n============================================================");
        if (error_count == 0)
            $display(" ALL TESTS PASSED ✓ — No errors detected.");
        else
            $display(" SIMULATION FAILED — %0d error(s) found.", error_count);
        $display("============================================================\n");

        $finish;
    end

    // =========================================================================
    // MONITOR — Prints every rising edge for waveform log
    // =========================================================================
    initial begin
        $display("\n--- Continuous Output Monitor ---");
        $monitor("T=%6t | CLK=%b RST=%b | NS[R=%b Y=%b G=%b] | EW[R=%b Y=%b G=%b]",
                 $time, clk, rst_n,
                 ns_red, ns_yellow, ns_green,
                 ew_red, ew_yellow, ew_green);
    end

endmodule

FPGA-Traffic-Light-Controller-main/waveforms/traffic_light_sim.vcd
$date
	Wed Jun 17 11:44:23 2026
$end
$version
	Icarus Verilog
$end
$timescale
	1ps
$end
$scope module tb_traffic_light_controller $end
$var wire 1 ! ns_yellow $end
$var wire 1 " ns_red $end
$var wire 1 # ns_green $end
$var wire 1 $ ew_yellow $end
$var wire 1 % ew_red $end
$var wire 1 & ew_green $end
$var parameter 4 ' GREEN_TIME $end
$var parameter 4 ( YELLOW_TIME $end
$var reg 1 ) clk $end
$var reg 1 * rst_n $end
$var integer 32 + error_count [31:0] $end
$scope module dut $end
$var wire 1 ) clk $end
$var wire 1 * rst_n $end
$var wire 1 , timer_done $end
$var parameter 4 - GREEN_TIME $end
$var parameter 2 . S0 $end
$var parameter 2 / S1 $end
$var parameter 2 0 S2 $end
$var parameter 2 1 S3 $end
$var parameter 4 2 YELLOW_TIME $end
$var reg 1 & ew_green $end
$var reg 1 % ew_red $end
$var reg 1 $ ew_yellow $end
$var reg 2 3 next_state [1:0] $end
$var reg 1 # ns_green $end
$var reg 1 " ns_red $end
$var reg 1 ! ns_yellow $end
$var reg 2 4 state [1:0] $end
$var reg 28 5 timer [27:0] $end
$upscope $end
$scope task check_state $end
$var reg 3 6 exp_ew [2:0] $end
$var reg 3 7 exp_ns [2:0] $end
$var reg 32 8 state_id [31:0] $end
$upscope $end
$scope task print_outputs $end
$var reg 64 9 timestamp [63:0] $end
$upscope $end
$upscope $end
$enddefinitions $end
$comment Show the parameter values. $end
$dumpall
b11 2
b11 1
b10 0
b1 /
b0 .
b1010 -
b11 (
b1010 '
$end
#0
$dumpvars
bx 9
bx 8
bx 7
bx 6
bx 5
bx 4
bx 3
x,
b0 +
0*
0)
x&
x%
x$
x#
x"
x!
$end
#5000
0,
1%
0$
0&
0"
0!
1#
b1 3
b0 5
b0 4
1)
#10000
0)
#15000
1)
#20000
0)
#25000
1)
#30000
0)
#35000
1)
#40000
0)
#45000
1)
#46000
1*
b0 8
b100 6
b1 7
#50000
0)
#55000
b1 5
1)
#60000
0)
#65000
b10 5
1)
#70000
0)
#75000
b11 5
1)
#80000
0)
#85000
b100 5
1)
#90000
0)
#95000
b101 5
1)
#100000
0)
#105000
b110 5
1)
#110000
0)
#115000
b111 5
1)
#120000
0)
#125000
b1000 5
1)
#130000
0)
#135000
1,
b1001 5
1)
#140000
0)
#145000
0,
b10 3
1!
0"
0#
b0 5
b1 4
1)
#150000
0)
#155000
b1 5
1)
#160000
0)
#165000
1,
b10 5
1)
#166000
b1 8
b10 7
#170000
0)
#175000
0,
1&
0%
1"
0!
b11 3
b10 4
b0 5
1)
#180000
0)
#185000
b1 5
1)
#190000
0)
#195000
b10 5
1)
#196000
b10 8
b1 6
b100 7
#200000
0)
#205000
b11 5
1)
#210000
0)
#215000
b100 5
1)
#220000
0)
#225000
b101 5
1)
#230000
0)
#235000
b110 5
1)
#240000
0)
#245000
b111 5
1)
#250000
0)
#255000
b1000 5
1)
#260000
0)
#265000
1,
b1001 5
1)
#270000
0)
#275000
0,
b0 3
1$
0%
0&
b11 4
b0 5
1)
#280000
0)
#285000
b1 5
1)
#290000
0)
#295000
1,
b10 5
1)
#296000
b11 8
b10 6
#300000
0)
#305000
0,
1#
0"
1%
0$
b1 3
b0 5
b0 4
1)
#310000
0)
#315000
b1 5
1)
#320000
0)
#325000
b10 5
1)
#326000
b0 8
b100 6
b1 7
#330000
0)
#335000
b11 5
1)
#340000
0)
#345000
b100 5
1)
#350000
0)
#355000
b101 5
1)
#360000
0)
#365000
b110 5
1)
#370000
0)
#375000
b0 5
0*
1)
#380000
0)
#385000
1)
#386000
1*
#390000
0)
#395000
b1 5
1)
#400000
0)
#405000
b10 5
1)
#410000
0)
#415000
b11 5
1)
#420000
0)
#425000
b100 5
1)
#430000
0)
#435000
b101 5
1)
#440000
0)
#445000
b110 5
1)
#450000
0)
#455000
b111 5
1)
#460000
0)
#465000
b1000 5
1)
#470000
0)
#475000
1,
b1001 5
1)
#480000
0)
#485000
0,
b10 3
1!
0"
0#
b0 5
b1 4
1)
#490000
0)
#495000
b1 5
1)
#500000
0)
#505000
1,
b10 5
1)
#510000
0)
#515000
0,
1&
0%
1"
0!
b11 3
b10 4
b0 5
1)
#520000
0)
#525000
b1 5
1)
#530000
0)
#535000
b10 5
1)
#540000
0)
#545000
b11 5
1)
#550000
0)
#555000
b100 5
1)
#560000
0)
#565000
b101 5
1)
#570000
0)
#575000
b110 5
1)
#580000
0)
#585000
b111 5
1)
#590000
0)
#595000
b1000 5
1)
#600000
0)
#605000
1,
b1001 5
1)
#610000
0)
#615000
0,
b0 3
1$
0%
0&
b11 4
b0 5
1)
#620000
0)
#625000
b1 5
1)
#630000
0)
#635000
1,
b10 5
1)
#640000
0)
#645000
0,
1#
0"
1%
0$
b1 3
b0 5
b0 4
1)
#650000
0)
#655000
b1 5
1)
#660000
0)
#665000
b10 5
1)
